Metadata-Version: 2.1
Name: certora-cli-alpha-niv-Fix-Path-In-Soroban-Entry
Version: 20241224.11.41.25008
Summary: Runner for the Certora Prover
Home-page: https://pypi.org/project/certora-cli-alpha-niv-Fix-Path-In-Soroban-Entry
Author: Certora
Author-email: support@certora.com
Classifier: Programming Language :: Python :: 3
Classifier: License :: OSI Approved :: MIT License
Classifier: Operating System :: OS Independent
Requires-Python: >=3.8
License-File: LICENSE
Requires-Dist: click
Requires-Dist: json5
Requires-Dist: pycryptodome
Requires-Dist: requests
Requires-Dist: rich
Requires-Dist: sly
Requires-Dist: tabulate
Requires-Dist: tqdm
Requires-Dist: StrEnum
Requires-Dist: tomli
Requires-Dist: universalmutator
